noaa_ghcn/__init__.py
noaa_ghcn/ghcn.py
noaa_ghcn/data/elements.txt
noaa_ghcn-0.3.0.dist-info/METADATA
noaa_ghcn-0.3.0.dist-info/WHEEL
noaa_ghcn-0.3.0.dist-info/licenses/LICENSE.md
noaa_ghcn-0.3.0.dist-info/RECORD
