Metadata-Version: 2.4
Name: noaa-ghcn
Version: 0.3.0
Summary: A package to retrieve data from the NOAA Global Historical Climatology Network Daily (GHCN-D) dataset on AWS S3.
Author-email: Colin Hill <colinalastairhill@gmail.com>
License:                     GNU GENERAL PUBLIC LICENSE
License-File: LICENSE.md
Classifier: Development Status :: 5 - Production/Stable
Classifier: License :: OSI Approved :: GNU General Public License v3 (GPLv3)
Classifier: Programming Language :: Python :: 3.10
Classifier: Programming Language :: Python :: 3.11
Classifier: Programming Language :: Python :: 3.12
Classifier: Programming Language :: Python :: 3.13
Requires-Python: >=3.10
Requires-Dist: boto3<2,>=1.36.24
Requires-Dist: geopandas
Requires-Dist: pandas
Requires-Dist: pyarrow
Requires-Dist: shapely
Requires-Dist: tqdm
